{"weather":{"suggestions":[{"title":"Weather for Lakeland","url":"https://www.accuweather.com/en/us/lakeland-fl/33801/current-weather/332280?lang=en-us&partner=web_mozilla_adc","provider":"accuweather","is_sponsored":false,"score":0.3,"city_name":"Lakeland","region_code":"FL","current_conditions":{"url":"https://www.accuweather.com/en/us/lakeland-fl/33801/current-weather/332280?lang=en-us&partner=web_mozilla_adc","summary":"Mostly cloudy","icon_id":6,"temperature":{"c":32,"f":90}},"forecast":{"url":"https://www.accuweather.com/en/us/lakeland-fl/33801/daily-weather-forecast/332280?lang=en-us&partner=web_mozilla_adc","summary":"Danger of dehydration and heat stroke if outside for extended periods of time this afternoon","high":{"c":35,"f":95},"low":{"c":22,"f":72}},"request_id":"b4f59e321f2b4702ade46f0f3b7342a7","source":"merino"}],"lastUpdated":1747598274283},"locationData":{"city":"Lakeland","adminArea":"","country":""}}